aiofbchat/__init__.py
aiofbchat/_client.py
aiofbchat/_common.py
aiofbchat/_events/__init__.py
aiofbchat/_events/_client_payload.py
aiofbchat/_events/_common.py
aiofbchat/_events/_delta_class.py
aiofbchat/_events/_delta_type.py
aiofbchat/_exception.py
aiofbchat/_fix_module_metadata.py
aiofbchat/_graphql.py
aiofbchat/_listen.py
aiofbchat/_models/__init__.py
aiofbchat/_models/_attachment.py
aiofbchat/_models/_common.py
aiofbchat/_models/_file.py
aiofbchat/_models/_location.py
aiofbchat/_models/_message.py
aiofbchat/_models/_plan.py
aiofbchat/_models/_poll.py
aiofbchat/_models/_quick_reply.py
aiofbchat/_models/_sticker.py
aiofbchat/_session.py
aiofbchat/_threads/__init__.py
aiofbchat/_threads/_abc.py
aiofbchat/_threads/_group.py
aiofbchat/_threads/_page.py
aiofbchat/_threads/_user.py
aiofbchat/_util.py
aiofbchat/py.typed
aiofbchat-0.1.0.dist-info/LICENSE.md
aiofbchat-0.1.0.dist-info/METADATA
aiofbchat-0.1.0.dist-info/WHEEL
aiofbchat-0.1.0.dist-info/RECORD
