Metadata-Version: 2.1
Name: aiofbchat
Version: 0.1.0
Summary: An Unofficial facebook messenger chat api.
License: LICENSE.md
Author: Muhammad MuQiT
Author-email: takasnashirikka8229@gmail.com
Requires-Python: >=3.10
Classifier: License :: Other/Proprietary License
Classifier: Programming Language :: Python :: 3
Classifier: Programming Language :: Python :: 3.10
Classifier: Programming Language :: Python :: 3.11
Classifier: Programming Language :: Python :: 3.12
Classifier: Programming Language :: Python :: 3.13
Requires-Dist: aiohttp (>=3.11.11,<4.0.0)
Requires-Dist: attrs (>=24.3.0,<25.0.0)
Requires-Dist: paho-mqtt (==1.6.1)
Requires-Dist: yarl (>=1.18.3,<2.0.0)
